beetsplug/__init__.py
beetsplug/drop2beets.py
examples/custom_tag.py
examples/force_genre_and_language_by_folder.py
examples/force_genre_by_folder.py
examples/skip_missing_title_or_artist.py
drop2beets-2.0.1.dist-info/LICENSE
drop2beets-2.0.1.dist-info/METADATA
drop2beets-2.0.1.dist-info/WHEEL
drop2beets-2.0.1.dist-info/RECORD
