Metadata-Version: 2.1
Name: drop2beets
Version: 2.0.1
Summary: Import singles to Beets as soon as they are dropped in a folder
Home-page: https://github.com/martinkirch/drop2beets
License: WTFPL
Keywords: watch,beets,music,import
Author: Martin Kirchgessner
Author-email: martin.kirch@gmail.com
Requires-Python: >=3.7,<4.0
Classifier: Development Status :: 5 - Production/Stable
Classifier: License :: Other/Proprietary License
Classifier: Programming Language :: Python :: 3
Classifier: Programming Language :: Python :: 3.7
Classifier: Programming Language :: Python :: 3.8
Classifier: Programming Language :: Python :: 3.9
Classifier: Programming Language :: Python :: 3.10
Classifier: Programming Language :: Python :: 3.11
Classifier: Programming Language :: Python :: 3.12
Classifier: Topic :: Multimedia :: Sound/Audio
Requires-Dist: watchdog (>=3.0.0,<4.0.0)
Project-URL: Repository, https://github.com/martinkirch/drop2beets.git
